{
	"$schema": "http://schema.management.azure.com/schemas/2015-01-01/deploymentTemplate.json#",
	"contentVersion": "1.0.0.0",
	"parameters": {
		"factoryName": {
			"type": "string",
			"metadata": "Data Factory name",
			"defaultValue": "adf-mongo-to-cosmos"
		},
		"AzureBlobStorage_connectionString": {
			"type": "secureString",
			"metadata": "Secure string for 'connectionString' of 'AzureBlobStorage'"
		},
		"MongoDbAtlas_connectionString": {
			"type": "secureString",
			"metadata": "Secure string for 'connectionString' of 'MongoDbAtlas'"
		},
		"CosmosDbMongoDbApi1_connectionString": {
			"type": "secureString",
			"metadata": "Secure string for 'connectionString' of 'CosmosDbMongoDbApi1'"
		},
		"AzureKeyVault1_properties_typeProperties_baseUrl": {
			"type": "string",
			"defaultValue": "https://dohoney-kv-adf.vault.azure.net/"
		},
		"MongoDbAtlas_properties_typeProperties_database": {
			"type": "string",
			"defaultValue": "sample_mflix"
		},
		"CosmosDbMongoDbApi1_properties_typeProperties_database": {
			"type": "string",
			"defaultValue": "mflix"
		}
	},
	"variables": {
		"factoryId": "[concat('Microsoft.DataFactory/factories/', parameters('factoryName'))]"
	},
	"resources": [
		{
			"name": "[concat(parameters('factoryName'), '/AzureBlobStorage')]",
			"type": "Microsoft.DataFactory/factories/linkedServices",
			"apiVersion": "2018-06-01",
			"properties": {
				"annotations": [],
				"type": "AzureBlobStorage",
				"typeProperties": {
					"connectionString": "[parameters('AzureBlobStorage_connectionString')]"
				}
			},
			"dependsOn": []
		},
		{
			"name": "[concat(parameters('factoryName'), '/AzureKeyVault1')]",
			"type": "Microsoft.DataFactory/factories/linkedServices",
			"apiVersion": "2018-06-01",
			"properties": {
				"annotations": [],
				"type": "AzureKeyVault",
				"typeProperties": {
					"baseUrl": "[parameters('AzureKeyVault1_properties_typeProperties_baseUrl')]"
				}
			},
			"dependsOn": []
		},
		{
			"name": "[concat(parameters('factoryName'), '/MongoDbAtlas')]",
			"type": "Microsoft.DataFactory/factories/linkedServices",
			"apiVersion": "2018-06-01",
			"properties": {
				"description": "Connection to my Personal MongoDB Instance",
				"annotations": [],
				"type": "MongoDbV2",
				"typeProperties": {
					"connectionString": "[parameters('MongoDbAtlas_connectionString')]",
					"database": "[parameters('MongoDbAtlas_properties_typeProperties_database')]"
				}
			},
			"dependsOn": []
		},
		{
			"name": "[concat(parameters('factoryName'), '/MongoDbV2Collection1')]",
			"type": "Microsoft.DataFactory/factories/datasets",
			"apiVersion": "2018-06-01",
			"properties": {
				"linkedServiceName": {
					"referenceName": "MongoDbAtlas",
					"type": "LinkedServiceReference"
				},
				"annotations": [],
				"type": "MongoDbV2Collection",
				"schema": [],
				"typeProperties": {
					"collection": "movies"
				}
			},
			"dependsOn": [
				"[concat(variables('factoryId'), '/linkedServices/MongoDbAtlas')]"
			]
		},
		{
			"name": "[concat(parameters('factoryName'), '/CosmosDbMongoDbApi1')]",
			"type": "Microsoft.DataFactory/factories/linkedServices",
			"apiVersion": "2018-06-01",
			"properties": {
				"annotations": [],
				"type": "CosmosDbMongoDbApi",
				"typeProperties": {
					"connectionString": "[parameters('CosmosDbMongoDbApi1_connectionString')]",
					"database": "[parameters('CosmosDbMongoDbApi1_properties_typeProperties_database')]"
				}
			},
			"dependsOn": []
		},
		{
			"name": "[concat(parameters('factoryName'), '/CosmosDbMongoDbApiCollection1')]",
			"type": "Microsoft.DataFactory/factories/datasets",
			"apiVersion": "2018-06-01",
			"properties": {
				"linkedServiceName": {
					"referenceName": "CosmosDbMongoDbApi1",
					"type": "LinkedServiceReference"
				},
				"annotations": [],
				"type": "CosmosDbMongoDbApiCollection",
				"schema": [],
				"typeProperties": {
					"collection": "movies"
				}
			},
			"dependsOn": [
				"[concat(variables('factoryId'), '/linkedServices/CosmosDbMongoDbApi1')]"
			]
		},
		{
			"name": "[concat(parameters('factoryName'), '/Copy To Cosmos')]",
			"type": "Microsoft.DataFactory/factories/pipelines",
			"apiVersion": "2018-06-01",
			"properties": {
				"activities": [
					{
						"name": "Copy MongoDB to Cosmos",
						"type": "Copy",
						"dependsOn": [],
						"policy": {
							"timeout": "7.00:00:00",
							"retry": 0,
							"retryIntervalInSeconds": 30,
							"secureOutput": false,
							"secureInput": false
						},
						"userProperties": [],
						"typeProperties": {
							"source": {
								"type": "MongoDbV2Source",
								"batchSize": 100
							},
							"sink": {
								"type": "CosmosDbMongoDbApiSink",
								"writeBatchTimeout": "00:30:00",
								"writeBatchSize": 1,
								"writeBehavior": "insert"
							},
							"enableStaging": false
						},
						"inputs": [
							{
								"referenceName": "MongoDbV2Collection1",
								"type": "DatasetReference",
								"parameters": {}
							}
						],
						"outputs": [
							{
								"referenceName": "CosmosDbMongoDbApiCollection1",
								"type": "DatasetReference",
								"parameters": {}
							}
						]
					}
				],
				"policy": {
					"elapsedTimeMetric": {},
					"cancelAfter": {}
				},
				"annotations": []
			},
			"dependsOn": [
				"[concat(variables('factoryId'), '/datasets/MongoDbV2Collection1')]",
				"[concat(variables('factoryId'), '/datasets/CosmosDbMongoDbApiCollection1')]"
			]
		}
	]
}